git_gpt/__init__.py
git_gpt/__main__.py
git_gpt/commit.py
git_gpt/status.py
git_gpt-0.3.0.dist-info/LICENSE
git_gpt-0.3.0.dist-info/METADATA
git_gpt-0.3.0.dist-info/WHEEL
git_gpt-0.3.0.dist-info/entry_points.txt
git_gpt-0.3.0.dist-info/top_level.txt
git_gpt-0.3.0.dist-info/RECORD
