Metadata-Version: 2.1
Name: git-gpt
Version: 0.3.0
Summary: Generate commit messages using OpenAI GPT-3.
Home-page: https://github.com/programmarchy/git-gpt
Author: Donald Ness
Author-email: donald.ness@gmail.com
License: MIT
Keywords: gpt,git
Classifier: Programming Language :: Python :: 3
Requires-Python: >=3.8
License-File: LICENSE
Requires-Dist: openai (>=0.26.1)
